bot_shared_models/__init__.py
bot_shared_models/bot_type.py
bot_shared_models/command/__init__.py
bot_shared_models/command/base/__init__.py
bot_shared_models/command/base/command.py
bot_shared_models/command/base/type.py
bot_shared_models/command/find_bot.py
bot_shared_models/command/start_bot/__init__.py
bot_shared_models/command/start_bot/parameters/__init__.py
bot_shared_models/command/start_bot/parameters/gmeet.py
bot_shared_models/command/start_bot/start_bot.py
bot_shared_models/command/start_recording.py
bot_shared_models/command/stop_recording.py
bot_shared_models/py.typed
bot_shared_models-0.3.0.dist-info/METADATA
bot_shared_models-0.3.0.dist-info/WHEEL
bot_shared_models-0.3.0.dist-info/RECORD
